Workbook

Sheet Leads
A1: First Name | B1: Last Name | C1: Position | D1: Company | E1: Company Size | F1: Industry | G1: Location | H1: Website | I1: LinkedIn URL | J1: Company LinkedIn | K1: Headline | L1: Position Dates | M1: Email | N1: Phone | O1: Intent Type | P1: Intent | Q1: Intent Keyword | R1: ICP Fit Score | S1: Intent Score | T1: Total Score | U1: Score Reasoning | V1: Open To Work | W1: Created (PHT) | X1: Export Status | Y1: Gojiberry Contact ID
A2: Riley | B2: Hennigh 🏴 | C2: Founder & Creative Director | D2: Oratory | E2: Myself Only | F2: Design Services | G2: Oklahoma City, Oklahoma, United States | H2: http://riley.cx | I2: https://www.linkedin.com/in/rileyhennigh | J2: https://linkedin.com/company/99470125 | K2: I help B2B software startups look and feel like established players. | L2: 02/01/2024 - Present | O2: RECENT_ACTIVITY | P2: Top 5% most active in your ICP (LinkedIn) | R2: 0.86 | S2: 1.2 | T2: 1.9 | U2: Founder aligns with ICP; Design Services in US; size slightly smaller but adjacent. | V2: No | W2: 2026-09-07 09:25 | X2: NEW - not yet exported | Y2: 17429758
A3: Laura | B3: Wachowiak (Antolak) | C3: Creative Director | D3: LJ Marketing & Media | E3: 1-10 employees | F3: Marketing Services | G3: San Diego, California, United States | I3: https://www.linkedin.com/in/laurawachowiak | J3: https://www.linkedin.com/company/lj-marketing-media | K3: Creative Operations & Marketing Leader | Brand, Content & Campaign Execution | Workflow Systems, Internal Communications & Team Delivery | L3: January 2025 - Present | O3: RECENT_ACTIVITY | P3: Top 5% most active in your ICP (LinkedIn) | R3: 0.96 | S3: 1.2 | T3: 2 | U3: Role, industry, and location align with the ICP; company size is one band smaller than the ICP. | V3: No | W3: 2026-09-07 09:25 | X3: NEW - not yet exported | Y3: 17429737
A4: Chloe | B4: Akahori | C4: Creative Director | D4: Domino New York | E4: 2-10 | F4: Design Services | G4: New York, New York, United States | H4: dominony.com | I4: https://www.linkedin.com/in/chloeakahori | J4: https://www.linkedin.com/company/dominonewyork | K4: Creative Director | L4: January 2019 - Present | O4: RECENT_ACTIVITY | P4: Top 5% most active in your ICP (LinkedIn) | R4: 0.98 | S4: 1.2 | T4: 2.1 | U4: Role and company fit ICP; location and industry align; strong all-around match. | V4: No | W4: 2026-09-07 09:25 | X4: NEW - not yet exported | Y4: 17429708
A5: Brendon | B5: McLean | C5: Owner | Creative Director | D5: Latitude Studios | E5: 1-10 employees | F5: Marketing Services | G5: Parkville, Maryland, United States | H5: http://www.latitudestudios.com | I5: https://www.linkedin.com/in/brendonmclean | J5: https://www.linkedin.com/company/latitude-studios | K5: Creative Director at Latitude Studios | L5: May 2007 - Present | O5: RECENT_ACTIVITY | P5: Top 5% most active in your ICP (LinkedIn) | R5: 0.89 | S5: 1.2 | T5: 1.9 | U5: Role aligns with ICP; US location; industry match; company size slightly smaller. | V5: No | W5: 2026-09-07 09:25 | X5: NEW - not yet exported | Y5: 17429704
A6: Kristin | B6: Wellmer | C6: Creative Director | D6: Crybaby Kingdom | E6: 1-10 employees | F6: Marketing Services | G6: Los Angeles, California, United States | H6: https://www.linkedin.com/redir/redirect?url=https://wellmer.co/&urlhash=Th50&trk=public_profile_topcard-website | I6: https://www.linkedin.com/in/wwwellmer | J6: https://www.linkedin.com/company/crybaby-kingdom | K6: Co-Founder @ Crybaby Kingdom / Executive Creative Director / Director / Writer | L6: May 2024 - Present | O6: RECENT_ACTIVITY | P6: Top 5% most active in your ICP (LinkedIn) | R6: 0.85 | S6: 1.2 | T6: 1.9 | U6: Creative Director in Marketing Services from US with near-fit company size aligns with ICP. | V6: No | W6: 2026-09-07 09:25 | X6: NEW - not yet exported | Y6: 17429699
A7: Kristine | B7: Jacobson | C7: Founder, CEO | D7: Conveyance Marketing Group | E7: 11-50 employees | F7: Marketing Services | G7: Leesburg, Virginia, United States | H7: http://www.conveyancemarketinggroup.com | I7: https://www.linkedin.com/in/kristinejacobsoncmo | J7: https://www.linkedin.com/company/conveyance-marketing-group | K7: Founder and CEO, Conveyance Marketing Group | L7: March 2009 - Present | O7: RECENT_ACTIVITY | P7: Top 5% most active in your ICP (LinkedIn) | R7: 0.96 | S7: 1.2 | T7: 2 | U7: Role aligns with ICP and location/industry/size match precisely. | V7: No | W7: 2026-09-07 09:24 | X7: NEW - not yet exported | Y7: 17429673
A8: Sulman | B8: Mirza | C8: Founder + Creative Director | D8: Resonant Design | E8: 2 - 10 | F8: Design Services | G8: Houston, Texas, United States | H8: https://resonant.work | I8: https://www.linkedin.com/in/sulmirza | J8: https://www.linkedin.com/company/resonant-studio/ | K8: Founder + Creative Director @ Resonant Design | Brand & Web | L8: 5/4/2025 - now | O8: RECENT_ACTIVITY | P8: Top 5% most active in your ICP (LinkedIn) | R8: 0.95 | S8: 1.2 | T8: 2 | U8: Role matches ICP; industry/location align; company size within allowed band. | V8: No | W8: 2026-09-07 09:24 | X8: NEW - not yet exported | Y8: 17429669
A9: Chad | B9: McCown | C9: Creative Director | D9: McCown Design Agency | E9: 1-10 employees | F9: Design Services | G9: Palos Verdes Peninsula, California, United States | H9: https://www.linkedin.com/redir/redirect?url=http://www.mccowndesignagency.com&urlhash=thwY&trk=public_profile_website | I9: https://www.linkedin.com/in/chadmccown | J9: https://www.linkedin.com/company/mccown-design-agency | K9: Creative Director @ McCown Design Agency • Illustration Representation @ Lemonade Illustration Agency | L9: 2005 - Present | O9: RECENT_ACTIVITY | P9: Top 5% most active in your ICP (LinkedIn) | R9: 0.83 | S9: 1.2 | T9: 1.8 | U9: Role matches ICP titles with seniority; location and industry align; company size slightly smaller than ICP but overall fit | V9: No | W9: 2026-09-07 09:24 | X9: NEW - not yet exported | Y9: 17429663
A10: Tierney | B10: Cunningham | C10: Creative Director | D10: Supermoon.us | E10: 1-10 employees | F10: Design Services | G10: Seattle, Washington, United States | H10: http://studiotierney.com | I10: https://www.linkedin.com/in/tierneycunningham | J10: https://linkedin.com/company/53174631 | K10: Brand Creative Director | L10: 08/01/2025 - Present | O10: RECENT_ACTIVITY | P10: Top 5% most active in your ICP (LinkedIn) | R10: 0.88 | S10: 1.2 | T10: 1.9 | U10: Creative Director aligns with ICP title; Design Services in US; company size close to ICP; location matches. | V10: No | W10: 2026-09-07 09:24 | X10: NEW - not yet exported | Y10: 17429637
A11: Noall-Scott | B11: Reid | C11: Founder / Creative Director | D11: Noall Scott | E11: 1-10 employees | F11: Marketing Services | G11: Greater Cleveland | H11: https://www.noallscott.com | I11: https://www.linkedin.com/in/noallreid | J11: https://www.linkedin.com/company/noall-scott | K11: Executive Creative Director | Creative Operations & Integrated Production Leader / Mountain Biking Enthusiast | L11: March 2008 - Present | O11: RECENT_ACTIVITY | P11: Top 5% most active in your ICP (LinkedIn) | R11: 0.92 | S11: 1.2 | T11: 2 | U11: Founder/Creative Director aligns with ICP; industry matches Marketing Services in US; location fits; size is just below ICP range. | V11: No | W11: 2026-09-07 09:24 | X11: NEW - not yet exported | Y11: 17429631
A12: Maria | B12: De La Cruz | C12: Founder / Creative Director | D12: Artropoliz | E12: Myself Only | F12: Design Services | G12: Redwood City, California, United States | H12: Artropoliz.com | I12: https://www.linkedin.com/in/maria-de-la-cruz-artropoliz | J12: https://www.linkedin.com/company/artropoliz | K12: Multidisciplinary Visual Designer | Illustrator | Founder, Artropoliz™ | Brand & Visual Storytelling | L12: March 2026 - Present | O12: RECENT_ACTIVITY | P12: Top 5% most active in your ICP (LinkedIn) | R12: 0.8 | S12: 1.2 | T12: 1.8 | U12: Role and location align with ICP; industry matches; company size does not. | V12: No | W12: 2026-09-07 09:24 | X12: NEW - not yet exported | Y12: 17429623
A13: Karine | B13: Makartichan | C13: Creative Director | D13: US Illustrations | E13: 11-50 employees | F13: Design Services | G13: Greater Boston | I13: https://www.linkedin.com/in/karine-makartichan | J13: https://www.linkedin.com/company/usillustrations | K13: Creative Director @US Illustrations | ABD Fine Arts, Character Design | L13: June 2017 - Present | O13: RECENT_ACTIVITY | P13: Top 5% most active in your ICP (LinkedIn) | R13: 0.96 | S13: 1.2 | T13: 2 | U13: Creative Director aligns with ICP roles and the company/region fit US marketing/design services. | V13: No | W13: 2026-09-07 09:24 | X13: NEW - not yet exported | Y13: 17429603
A14: Austin | B14: Robinson | C14: Founder, Head of Creative | D14: Absorb Studios | E14: 2 - 10 | F14: Advertising Services | G14: Greater Indianapolis | H14: www.Austin-Robinson.com | I14: https://www.linkedin.com/in/austin-robinson-b1b53a157 | J14: https://www.linkedin.com/company/absorbstudios | K14: Founder & Head of Creative, Cinematographer at Absorb Studios | L14: December 2022 - Present | O14: RECENT_ACTIVITY | P14: Top 5% most active in your ICP (LinkedIn) | R14: 0.92 | S14: 1.2 | T14: 2 | U14: Role aligns with ICP; industry/location/size match US Advertising Services. | V14: No | W14: 2026-09-07 09:24 | X14: NEW - not yet exported | Y14: 17429573
A15: Brooke | B15: White | C15: Client Success Manager | D15: Moonlight Digital | E15: 2-10 | F15: Marketing Services | G15: Highland, Michigan, United States | I15: https://www.linkedin.com/in/brooke-white-b5b763264 | J15: https://www.linkedin.com/company/moonlight-digital | K15: Client Success Manager | L15: May 2025 - Present | O15: RECENT_ACTIVITY | P15: Top 5% most active in your ICP (LinkedIn) | R15: 1 | S15: 1.2 | T15: 2.1 | U15: Role aligns with ICP titles; industry, location, and company size match the ICP criteria. | V15: No | W15: 2026-09-07 09:24 | X15: NEW - not yet exported | Y15: 17429569
A16: Nathan | B16: Orensten | C16: Creative Director | D16: READY SET NO | E16: 1-10 employees | F16: Marketing Services | G16: Columbus, Ohio, United States | I16: https://www.linkedin.com/in/nathan-orensten | J16: https://www.linkedin.com/company/ready-set-no | K16: Creative Director | L16: May 2025 - Present | O16: RECENT_ACTIVITY | P16: Top 5% most active in your ICP (LinkedIn) | R16: 1 | S16: 1.2 | T16: 2.1 | U16: Role, industry, location and size align with ICP. | V16: No | W16: 2026-09-07 09:24 | X16: NEW - not yet exported | Y16: 17429566
A17: Madi | B17: Balman | C17: Founder & Creative Director | D17: Skellydog | E17: 1-10 employees | F17: Marketing Services | G17: Norwich, Connecticut, United States | H17: www.skellydog.com | I17: https://www.linkedin.com/in/mnbalman | J17: https://www.linkedin.com/company/skellydog | K17: Brand Strategist & Creative Director | Fierce Advocate for Growing Bold, Strategy-Driven Brands | L17: 01/01/2016 - Present | O17: RECENT_ACTIVITY | P17: Top 5% most active in your ICP (LinkedIn) | R17: 0.94 | S17: 1.2 | T17: 2 | U17: Founder's role aligns with ICP; industry and location match US marketing services; company size slightly smaller but adjacent. | V17: No | W17: 2026-09-07 09:24 | X17: NEW - not yet exported | Y17: 17429515
A18: Ralph | B18: Renna | C18: Client Success Manager | D18: HeavySet Tech | E18: 1-10 employees | F18: Marketing Services | G18: Dallas-Fort Worth Metroplex | I18: https://www.linkedin.com/in/ralph-renna | J18: https://www.linkedin.com/company/heavy-set-tech | K18: Client Success Manager | AI-Powered Lead Acquisition & 24/7 Automated Scheduling to Scale Businesses. Focused on Contractor Growth Strategies and Lead Optimization. | L18: May 2026 - Present | O18: RECENT_ACTIVITY | P18: Top 5% most active in your ICP (LinkedIn) | R18: 0.9 | S18: 1.2 | T18: 2 | U18: Role matches ICP, location/industry align, company size close to ICP; scoring reflects near-fit with a modest size delta. | V18: No | W18: 2026-09-07 09:24 | X18: NEW - not yet exported | Y18: 17429514
A19: Michael | B19: Terranova | C19: Creative Director | D19: Fletcher Knight | E19: 11-50 employees | F19: Marketing Services | G19: New York City Metropolitan Area | H19: http://www.fletcherknight.com | I19: https://www.linkedin.com/in/michael-terranova-61321a29 | J19: https://www.linkedin.com/company/fletcherknight | K19: Creative Director at Fletcher Knight | L19: January 2014 - Present | O19: RECENT_ACTIVITY | P19: Top 5% most active in your ICP (LinkedIn) | R19: 0.97 | S19: 1.2 | T19: 2 | U19: Role and company fit ICP: Creative Director in Marketing Services, US. | V19: No | W19: 2026-09-07 09:24 | X19: NEW - not yet exported | Y19: 17429511
A20: Molly | B20: Durchholz | C20: Co-Founder & Creative Director | D20: Common Thread | E20: 1-10 employees | F20: Design Services | G20: Evansville, Indiana, United States | H20: mjdursigns.myportfolio.com | I20: https://www.linkedin.com/in/molly-durchholz-983403244 | J20: https://www.linkedin.com/company/ownyourthread | K20: Co-Founder & Creative Director | Common Thread Co. | L20: January 2026 - Present | O20: RECENT_ACTIVITY | P20: Top 5% most active in your ICP (LinkedIn) | R20: 0.87 | S20: 1.2 | T20: 1.9 | U20: Role maps to ICP titles; location is US and industry aligns; company size is one band below ICP. | V20: No | W20: 2026-09-07 09:24 | X20: NEW - not yet exported | Y20: 17429502
A21: Timothy | B21: Miley | C21: Founder / Head of Creative | D21: Miley Studios | E21: 2-10 | F21: Advertising Services | G21: Greater Reno Area, United States | H21: https://mileystudios.com | I21: https://www.linkedin.com/in/timmiley | J21: https://www.linkedin.com/company/miley-studios/ | K21: Founder, Miley Studios | Ad Person of the Year | Brand Strategy & Digital Marketing | 400+ Awards incl. Webby | L21: 1/01/2023 - now | O21: RECENT_ACTIVITY | P21: Top 5% most active in your ICP (LinkedIn) | R21: 0.96 | S21: 1.2 | T21: 2 | U21: Role and ICP align on title, industry, location, and company size. | V21: No | W21: 2026-09-07 09:24 | X21: NEW - not yet exported | Y21: 17429446
A22: Dan | B22: Cowling | C22: Agency Founder, President & CEO | D22: The Communications Group, Inc. | E22: 11 - 50 | F22: Advertising Services | G22: Little Rock, Arkansas, United States | H22: http://www.comgroup.com | I22: https://www.linkedin.com/in/dan-cowling-4a92a120 | J22: https://www.linkedin.com/company/the-communications-group-inc. | K22: Founder, President & CEO The Communications Group, Inc. | L22: 1987 - Present | O22: RECENT_ACTIVITY | P22: Top 5% most active in your ICP (LinkedIn) | R22: 0.96 | S22: 1.2 | T22: 2 | U22: Role maps to Founder/CEO and location and size fit the ICP. | V22: No | W22: 2026-09-07 09:24 | X22: NEW - not yet exported | Y22: 17429436
A23: Dominica | B23: Fehlau | C23: Client Success Manager | D23: TKX Media | E23: 11-50 | F23: Marketing Services | G23: St. Petersburg, Florida, United States | H23: https://nikaworldwide.wixsite.com/nika | I23: https://www.linkedin.com/in/dominica-fehlau | J23: https://www.linkedin.com/company/tkx-media | K23: Client Success Manager | Digital Marketing & Project Management — Campaign Strategy, Automation, CRM & AI | L23: December 2025 - Present | O23: RECENT_ACTIVITY | P23: Top 5% most active in your ICP (LinkedIn) | R23: 0.96 | S23: 1.2 | T23: 2 | U23: Role aligns with ICP; industry, location, and size match closely. | V23: No | W23: 2026-09-07 09:24 | X23: NEW - not yet exported | Y23: 17429391
A24: Caylin | B24: Sanders | C24: President, Founder & CEO | D24: EscapeMaker | E24: 1-10 employees | F24: Marketing Services | G24: Saugerties, New York, United States | H24: http://www.escapemaker.com | I24: https://www.linkedin.com/in/caylinsanders | J24: https://www.linkedin.com/company/escapemaker | K24: President, Founder and CEO at EscapeMaker.com | L24: September 2000 - Present | O24: RECENT_ACTIVITY | P24: Top 5% most active in your ICP (LinkedIn) | R24: 0.88 | S24: 1.2 | T24: 1.9 | U24: Executive founder/CEO match in US marketing services with near-ICP company size and location. | V24: No | W24: 2026-09-07 09:24 | X24: NEW - not yet exported | Y24: 17429390
A25: Matt | B25: Fantastic | C25: Creative Director | D25: Forever Stoked Creative | E25: 1-10 employees | F25: Design Services | G25: New Haven, Connecticut, United States | I25: https://www.linkedin.com/in/matt-fantastic | J25: https://www.linkedin.com/company/forever-stoked-creative | K25: Creative Director at Forever Stoked Creative | L25: 2007 - Present | O25: RECENT_ACTIVITY | P25: Top 5% most active in your ICP (LinkedIn) | R25: 0.82 | S25: 1.2 | T25: 1.8 | U25: Creative Director aligns with ICP title; Design Services in US; company size slightly smaller. | V25: No | W25: 2026-09-07 09:24 | X25: NEW - not yet exported | Y25: 17429387
A26: Christopher | B26: Carroll | C26: Art Director | D26: GradComm | E26: 11-50 | F26: Marketing Services | G26: United States | H26: https://www.krop.com/ccarr2222/ | I26: https://www.linkedin.com/in/christopher-james-carroll | J26: https://www.linkedin.com/company/gradcomm | K26: Design Professional & Creative Team Lead | L26: April 2024 - Present | O26: RECENT_ACTIVITY | P26: Top 5% most active in your ICP (LinkedIn) | R26: 1 | S26: 1.2 | T26: 2.1 | U26: Role, industry, size, and location align with the ICP. | V26: No | W26: 2026-09-07 09:24 | X26: NEW - not yet exported | Y26: 17429385
A27: Arlyn | B27: Hernandez | C27: Creative Director, Founder | D27: Biotonic Design | E27: 1-10 employees | F27: Design Services | G27: Miami, Florida, United States | H27: http://www.arlynhernandez.com | I27: https://www.linkedin.com/in/arlynhernandezmiami | J27: https://www.linkedin.com/company/biotonicdesign | K27: Creative Director at Biotonic, Founder at SAUSHI | L27: 2008 - Present | O27: RECENT_ACTIVITY | P27: Top 5% most active in your ICP (LinkedIn) | R27: 0.94 | S27: 1.2 | T27: 2 | U27: Strong fit: senior Creative Director/Founder at a US design services firm. | V27: No | W27: 2026-09-07 09:24 | X27: NEW - not yet exported | Y27: 17429341
A28: Jennifer | B28: Grinnell | C28: President/Creative Director | D28: BrandPlanet, LLC | E28: 1-10 employees | F28: Marketing Services | G28: Washington DC-Baltimore Area | H28: http://www.brandplanet.net | I28: https://www.linkedin.com/in/jennifer-grinnell-1940534 | J28: https://www.linkedin.com/company/brandplanet | K28: Creative Director I Brand Developer I Communications Strategist I Copywriter I Educator I Founder & President of Ellanor C. Lawrence Park Friends | L28: January 1999 - Present | O28: RECENT_ACTIVITY | P28: Top 5% most active in your ICP (LinkedIn) | R28: 0.84 | S28: 1.2 | T28: 1.9 | U28: Role and industry align with ICP; location in US and size near ICP but slightly smaller. | V28: No | W28: 2026-09-07 09:24 | X28: NEW - not yet exported | Y28: 17429337
A29: Holly | B29: Timmins | C29: Creative Director | D29: Creative Design Squared | E29: 1-10 employees | F29: Marketing Services | G29: Argyle, Texas, United States | H29: http://creativedesignsquared.com/ | I29: https://www.linkedin.com/in/holly-timmins-ab473250 | J29: https://www.linkedin.com/company/cdsquared | K29: Creative Director at Creative Design Squared | L29: November 2023 - Present | O29: RECENT_ACTIVITY | P29: Top 5% most active in your ICP (LinkedIn) | R29: 0.88 | S29: 1.2 | T29: 1.9 | U29: Role aligns with ICP; industry and location match US-based marketing services; company size is near ICP band. | V29: No | W29: 2026-09-07 09:24 | X29: NEW - not yet exported | Y29: 17429332
A30: Angelica | B30: Cifuentes Hernandez | C30: Founder - Creative Director | D30: Presentora designs | E30: 1-10 employees | F30: Marketing Services | G30: Chicago, Illinois, United States | H30: https://www.linkedin.com/redir/redirect?url=www.presentora.com&urlhash=V0Oa&trk=public_profile_topcard-website | I30: https://www.linkedin.com/in/angelicacifuentes | J30: https://www.linkedin.com/company/presentora-designs | K30: Breathing life into your presentations | Presentation Specialist & Creative Director | L30: February 2023 - Present | O30: RECENT_ACTIVITY | P30: Top 5% most active in your ICP (LinkedIn) | R30: 0.96 | S30: 1.2 | T30: 2 | U30: Founder/Creative Director in US marketing services aligns with ICP. | V30: No | W30: 2026-09-07 09:24 | X30: NEW - not yet exported | Y30: 17429329
A31: Niyati | B31: Kothary Shah | C31: Founder, Creative Director | D31: Create Forward | E31: 1-10 employees | F31: Design Services | G31: New York City Metropolitan Area | I31: https://www.linkedin.com/in/niyati-kothary-shah-a2103516 | J31: https://linkedin.com/company/92935001 | K31: Founder @ Create Forward | Bespoke design studio for CMOs + CGOs | Strategy, narrative & design for growth teams to secure funding, win clients & scale | Follow for more on strategic communication design | Ex-consulting | L31: 11/01/2008 - Present | O31: RECENT_ACTIVITY | P31: Top 5% most active in your ICP (LinkedIn) | R31: 0.9 | S31: 1.2 | T31: 2 | U31: Role aligns as Founder/Creative Director; industry Design Services; location US; company size near ICP. | V31: No | W31: 2026-09-07 09:24 | X31: NEW - not yet exported | Y31: 17429314
A32: Mike | B32: Conway | C32: Creative Director | D32: Jump Company | E32: 11-50 employees | F32: Marketing Services | G32: St Louis, Missouri, United States | H32: http://jumpcompany.com/ | I32: https://www.linkedin.com/in/mike-conway-a2095316 | J32: https://www.linkedin.com/company/jump-company | K32: Creative Director, Art Director, Graphic Designer for Advertising & Marketing | L32: April 2008 - Present | O32: RECENT_ACTIVITY | P32: Top 5% most active in your ICP (LinkedIn) | R32: 1 | S32: 1.2 | T32: 2.1 | U32: Profile aligns exactly with the ICP across title, industry, size, and location. | V32: No | W32: 2026-09-07 09:24 | X32: NEW - not yet exported | Y32: 17429313
A33: Lane | B33: Banning | C33: Founder, Creative Director | D33: UFO | E33: 1-10 employees | F33: Marketing Services | G33: New York, New York, United States | H33: www.lanebanning.com | I33: https://www.linkedin.com/in/lanebanning | J33: https://www.linkedin.com/company/ufoglobal | K33: label head & creative director | L33: June 2023 - Present | O33: RECENT_ACTIVITY | P33: Top 5% most active in your ICP (LinkedIn) | R33: 0.96 | S33: 1.2 | T33: 2 | U33: Founder title matches ICP, industry and location align, and company size is near ICP range. | V33: No | W33: 2026-09-07 09:24 | X33: NEW - not yet exported | Y33: 17429306
A34: Gabrielle | B34: Raumberger | C34: President, Creative Director | D34: EPOS Inc | E34: 1-10 employees | F34: Design Services | G34: Hermosa Beach, California, United States | H34: http://www.eposinc.com | I34: https://www.linkedin.com/in/gabrielle-raumberger-8975ab1 | J34: https://www.linkedin.com/company/epos-inc | K34: Creative Director, EPOS Inc., Brand Strategy and Design Studio | L34: 1990 - Present | O34: RECENT_ACTIVITY | P34: Top 5% most active in your ICP (LinkedIn) | R34: 0.84 | S34: 1.2 | T34: 1.9 | U34: Role and location strongly align; industry matches; company size is slightly off ICP bands. | V34: No | W34: 2026-09-07 09:24 | X34: NEW - not yet exported | Y34: 17429301
A35: Brandon | B35: Locke | C35: Founder, Art Director | D35: Studio Vermilion | E35: 1-10 employees | F35: Design Services | G35: Detroit Metropolitan Area | H35: https://www.Brandon-Locke.com | I35: https://www.linkedin.com/in/brandon-locke-35a14927 | J35: https://www.linkedin.com/company/studio-vermilion | K35: Freelance Creative, Art | Prev.  | Co-Director, Studio Vermilion | L35: November 2023 - Present | O35: RECENT_ACTIVITY | P35: Top 5% most active in your ICP (LinkedIn) | R35: 0.87 | S35: 1.2 | T35: 1.9 | U35: Founder in Design Services (US) with suitable company size; location match. | V35: No | W35: 2026-09-07 09:24 | X35: NEW - not yet exported | Y35: 17429296
A36: Aften | B36: Bell | C36: Founder & Creative Director | D36: Aften Design Studio | E36: 1-10 employees | F36: Design Services | G36: Dallas, Texas, United States | H36: http://www.aftenbell.com | I36: https://www.linkedin.com/in/aften-bell | J36: https://www.linkedin.com/company/aften-design-studio | K36: Founder & Creative Director at Aften Design Studio | Founder at The Love Pit Rescue | L36: January 2017 - Present | O36: RECENT_ACTIVITY | P36: Top 5% most active in your ICP (LinkedIn) | R36: 0.95 | S36: 1.2 | T36: 2 | U36: Role and industry align with the ICP; location matches; company size is close to ICP. | V36: No | W36: 2026-09-07 09:24 | X36: NEW - not yet exported | Y36: 17429281
A37: Nourhan | B37: Wahdan | C37: Founder & Creative Director | D37: pew. design bureau | E37: 2 - 10 | F37: Design Services | G37: Los Angeles Metropolitan Area | H37: Pewdesign.com | I37: https://www.linkedin.com/in/nourhanwahdan | J37: https://www.linkedin.com/company/pewdesignbureau | K37: Brand Strategist + Creative Director | Self-Proclaimed Toyfication Expert | Founder @ pew. design bureau | Top 3% LinkedIn Creator Worldwide | L37: September 2017 - Present | O37: RECENT_ACTIVITY | P37: Top 5% most active in your ICP (LinkedIn) | R37: 0.96 | S37: 1.2 | T37: 2 | U37: Role and company fit the ICP; industry, size, and US location align. | V37: No | W37: 2026-09-07 09:24 | X37: NEW - not yet exported | Y37: 17429276
A38: Syed Zuhair | B38: Zaidi | C38: Co-Founder & Creative Director | D38: ZHSync Digital | E38: 1-10 employees | F38: Marketing Services | G38: United States | I38: https://www.linkedin.com/in/zuhair-personal-branding | J38: https://www.linkedin.com/company/zhsync/ | K38: Co-Founder & Creative Director, ZHSync Digital | Brand systems + creative that grow profitable brands. | L38: 1/11/2024 - now | O38: RECENT_ACTIVITY | P38: Top 5% most active in your ICP (LinkedIn) | R38: 0.96 | S38: 1.2 | T38: 2 | U38: Role maps to Founder/Creative Director; industry and location align with the ICP; size is close to ICP bands. | V38: No | W38: 2026-09-07 09:24 | X38: NEW - not yet exported | Y38: 17429264
A39: Matt | B39: Yerman | C39: Creative Director, Founder | D39: Study Hall Studio | E39: 11-50 | F39: Design Services | G39: San Francisco Bay Area | H39: http://www.madeservice.net | I39: https://www.linkedin.com/in/matt-yerman-205a105b | J39: https://www.linkedin.com/company/studyhalldesign | K39: Co-Founder / Creative Director at Study Hall | L39: September 2020 - Present | O39: RECENT_ACTIVITY | P39: Top 5% most active in your ICP (LinkedIn) | R39: 1 | S39: 1.2 | T39: 2.1 | U39: Role, industry, location, and company size align with the ICP. | V39: No | W39: 2026-09-07 09:24 | X39: NEW - not yet exported | Y39: 17429259
A40: Mark | B40: Dreistadt | C40: President & CEO | D40: IDEX Pro | E40: 1-10 employees | F40: Marketing Services | G40: Export, Pennsylvania, United States | H40: http://www.infinityconcepts.com | I40: https://www.linkedin.com/in/markdreistadt | J40: https://www.linkedin.com/company/idex-pro | K40: Founder, President & CEO at Infinity Concepts and Inspire Media Group | L40: January 2024 - Present | O40: RECENT_ACTIVITY | P40: Top 5% most active in your ICP (LinkedIn) | R40: 0.9 | S40: 1.2 | T40: 2 | U40: Role aligns with ICP (Founder/CEO), industry and US location match; company size is slightly smaller than ICP. | V40: No | W40: 2026-09-07 09:24 | X40: NEW - not yet exported | Y40: 17429255
A41: Nichole | B41: Rouillac | C41: Founder + Creative Director | D41: level | E41: 1-10 employees | F41: Design Services | G41: San Francisco, California, United States | H41: https://leveldesignsf.com | I41: https://www.linkedin.com/in/nicholerouillac | J41: https://www.linkedin.com/company/level-design-sf/ | K41: Founder + Creative Director at level | L41: 01/9/2016 - now | O41: RECENT_ACTIVITY | P41: Top 5% most active in your ICP (LinkedIn) | R41: 0.96 | S41: 1.2 | T41: 2 | U41: Founder/Creative Director at a Design Services firm in the US aligns with ICP roles and location. | V41: No | W41: 2026-09-07 09:24 | X41: NEW - not yet exported | Y41: 17429254
A42: Amy | B42: Draheim | C42: President & Founder | D42: ABD Creative | E42: 1-10 employees | F42: Marketing Services | G42: Bend, Oregon, United States | H42: amydraheim.com | I42: https://www.linkedin.com/in/amy-draheim | J42: https://www.linkedin.com/company/abd-creative | K42: We bring people to hotels, and hotels to people. Founder of ABD Creative and published author. | L42: July 2017 - Present | O42: RECENT_ACTIVITY | P42: Top 5% most active in your ICP (LinkedIn) | R42: 0.92 | S42: 1.2 | T42: 2 | U42: Founder/President at a Marketing Services firm aligns with ICP. | V42: No | W42: 2026-09-07 09:24 | X42: NEW - not yet exported | Y42: 17429250
A43: Fernando | B43: Lozano Montalvo | C43: CEO & Founder | Creative Director | D43: Fenigs | E43: 11-50 employees | F43: Design Services | G43: El Paso, Texas, United States | I43: https://www.linkedin.com/in/fernandolozanomontalvo | J43: https://www.linkedin.com/company/fenigsinterdesign | K43: Creative Director — Executive Storytelling, Live Experiences & Multimedia Systems | L43: April 2019 - Present | O43: RECENT_ACTIVITY | P43: Top 5% most active in your ICP (LinkedIn) | R43: 1 | S43: 1.2 | T43: 2.1 | U43: Role and company fit ICP; location, size, and industry align with the ICP. | V43: No | W43: 2026-09-07 09:24 | X43: NEW - not yet exported | Y43: 17429236
A44: Raphael | B44: Farasat | C44: Founder & Creative Director | D44: Truffl | E44: 2 - 10 | F44: Design Services | G44: Los Angeles, California, United States | H44: https://truffl.com | I44: https://www.linkedin.com/in/raphaelfarasat | J44: https://www.linkedin.com/company/truffl/ | K44: Founder & Creative Director at Truffl Branding Agency | L44: 2/8/2014 - now | O44: RECENT_ACTIVITY | P44: Top 5% most active in your ICP (LinkedIn) | R44: 1 | S44: 1.2 | T44: 2.1 | U44: Role and company align with ICP; located in US; industry matches. | V44: No | W44: 2026-09-07 09:24 | X44: NEW - not yet exported | Y44: 17429234
A45: ken | B45: Griffen | C45: Creative Director | D45: HI-VIS.WORLD | E45: 1-10 employees | F45: Design Services | G45: New York, New York, United States | H45: part02.com | I45: https://www.linkedin.com/in/ken-griffen | J45: https://www.linkedin.com/company/hi-vis-world | K45: Founder / Head of Creative @ hi-vis.world | Video Direction, Photo Direction, Branding specializing in athletics | L45: January 2023 - Present | O45: RECENT_ACTIVITY | P45: Top 5% most active in your ICP (LinkedIn) | R45: 0.9 | S45: 1.2 | T45: 2 | U45: Creative Director in Design Services in the US aligns with ICP criteria. | V45: No | W45: 2026-09-07 09:24 | X45: NEW - not yet exported | Y45: 17429223
A46: Zelda | B46: E | C46: Founder + Creative Director | D46: Strength Marks | E46: Myself Only | F46: Marketing Services | G46: San Francisco, California, United States | H46: https://www.strengthmarks.com/ | I46: https://www.linkedin.com/in/zelda-elisco | J46: https://www.linkedin.com/company/strength-marks | K46: Body-Empowerment Marketing | Founder, Strength Marks | L46: June 2018 - Present | O46: RECENT_ACTIVITY | P46: Top 5% most active in your ICP (LinkedIn) | R46: 0.8 | S46: 1.2 | T46: 1.8 | U46: Founder with ICP role matches; location/industry align; company size below ICP band. | V46: No | W46: 2026-09-07 09:24 | X46: NEW - not yet exported | Y46: 17429207
A47: Julie | B47: Stanescu | C47: Founder & CEO | D47: RETHINK | E47: 1-10 employees | F47: Design Services | G47: San Francisco, California, United States | H47: https://www.linkedin.com/redir/redirect?url=http://www.rethinkhq.com&urlhash=SnlJ&trk=public_profile_topcard-website | I47: https://www.linkedin.com/in/juliestanescu | J47: https://www.linkedin.com/company/rethinkhq | K47: Founder | Strategic Events | Creating curated learning experiences that connect you with the people who matter most. | L47: March 2017 - Present | O47: RECENT_ACTIVITY | P47: Top 5% most active in your ICP (LinkedIn) | R47: 0.98 | S47: 1.2 | T47: 2.1 | U47: Role aligns with Founder/CEO; industry matches Design Services; US location; company size close to ICP. | V47: No | W47: 2026-09-07 09:24 | X47: NEW - not yet exported | Y47: 17429195
A48: Luke | B48: Cline | C48: Founder / Creative Director | D48: Relative Scale | E48: 11-50 employees | F48: Design Services | G48: Raleigh, North Carolina, United States | H48: http://www.relativescale.com | I48: https://www.linkedin.com/in/lukecline | J48: https://www.linkedin.com/company/relative-scale | K48: Founder / Creative Director at Relative Scale | L48: March 2018 - Present | O48: RECENT_ACTIVITY | P48: Top 5% most active in your ICP (LinkedIn) | R48: 0.98 | S48: 1.2 | T48: 2.1 | U48: Founder/Creative Director at a US design services firm aligns with ICP. | V48: No | W48: 2026-09-07 09:24 | X48: NEW - not yet exported | Y48: 17429189
A49: Trevor | B49: McCool | C49: CEO / Creative Director | D49: Born Movement | E49: 1-10 employees | F49: Marketing Services | G49: Colorado Springs, Colorado, United States | H49: https://bornmovement.com | I49: https://www.linkedin.com/in/trevor-mccool-46190823 | J49: https://www.linkedin.com/company/born-movement | K49: Born Movement - CEO / Creative Director | L49: July 2025 - Present | O49: RECENT_ACTIVITY | P49: Top 5% most active in your ICP (LinkedIn) | R49: 1 | S49: 1.2 | T49: 2.1 | U49: Role and company fit, industry, size, and US location match ICP. | V49: No | W49: 2026-09-07 09:24 | X49: NEW - not yet exported | Y49: 17429187
A50: Jamie | B50: Feldheim | C50: Creative Director | D50: Joyride Marketing | E50: 1-10 employees | F50: Marketing Services | G50: Louisville, Kentucky, United States | H50: http://www.jamiefeldheim.com | I50: https://www.linkedin.com/in/jamie-feldheim-b5939b78 | J50: https://www.linkedin.com/company/joyride-marketing | K50: Creative Director / Partner at Joyride Marketing | Leading startup brand acceleration and creative strategies | L50: February 2023 - Present | O50: RECENT_ACTIVITY | P50: Top 5% most active in your ICP (LinkedIn) | R50: 0.92 | S50: 1.2 | T50: 2 | U50: Role, industry, and location align with ICP; company size slightly outside but adjacent. | V50: No | W50: 2026-09-07 09:24 | X50: NEW - not yet exported | Y50: 17429181
A51: Niko | B51: Niarhos | C51: Creative Director | D51: Flex Marketing | E51: 11-50 employees | F51: Marketing Services | G51: Ossining, New York, United States | I51: https://www.linkedin.com/in/niko-niarhos-35655127 | J51: https://www.linkedin.com/company/flexmktng | K51: Creative Director (Art) | L51: December 2025 - Present | O51: RECENT_ACTIVITY | P51: Top 5% most active in your ICP (LinkedIn) | R51: 1 | S51: 1.2 | T51: 2.1 | U51: Role, industry, location, and company size all align with the ICP. | V51: No | W51: 2026-09-07 09:24 | X51: NEW - not yet exported | Y51: 17429174
A52: Teri | B52: Hagemann | C52: Director of Client Services | D52: Splash Clinical | E52: 11-50 employees | F52: Marketing Services | G52: Milwaukee, Wisconsin, United States | I52: https://www.linkedin.com/in/teri-hagemann-9104703 | J52: https://linkedin.com/company/10652064 | K52: Director of Client Services at Splash Clinical · Keeping trials enrolling — first patient in to last patient out | L52: 03/01/2023 - Present | O52: RECENT_ACTIVITY | P52: Top 5% most active in your ICP (LinkedIn) | R52: 0.94 | S52: 1.2 | T52: 2 | U52: Direct match on role, industry, size, and location with ICP expectations. | V52: No | W52: 2026-09-07 09:24 | X52: NEW - not yet exported | Y52: 17429168
A53: Hazn | B53: Rizz | C53: Co-Founder & Design Lead | D53: Design4Conversion | E53: 2-10 | F53: Design Services | G53: United States | H53: design4conversion.com | I53: https://www.linkedin.com/in/haznsyed | J53: https://www.linkedin.com/company/design4conversion | K53: Co-Founder & Design Lead @ Design4Conversion | Web Design, Web Development | L53: July 2018 - Present | O53: RECENT_ACTIVITY | P53: Top 5% most active in your ICP (LinkedIn) | R53: 0.94 | S53: 1.2 | T53: 2 | U53: Founder-level role in Design Services within US aligns with ICP. | V53: No | W53: 2026-09-07 09:24 | X53: NEW - not yet exported | Y53: 17429150
A54: Arslan | B54: Khaliq | C54: Creative Director | D54: 10Thirteen | E54: 1-10 employees | F54: Design Services | G54: Garland, Texas, United States | I54: https://www.linkedin.com/in/arslan-khaliq-82410746 | J54: https://www.linkedin.com/company/10thirteen | K54: Creative Director | Senior Brand & Campaign Designer | AI-Driven Creative | SaaS & B2B | Ex-Salesforce, Samsung | Dallas / Remote | L54: May 2025 - Present | O54: RECENT_ACTIVITY | P54: Top 5% most active in your ICP (LinkedIn) | R54: 0.92 | S54: 1.2 | T54: 2 | U54: Creative Director role aligns with ICP; industry and location fit; company size slightly smaller but within acceptable band. | V54: No | W54: 2026-09-07 09:24 | X54: NEW - not yet exported | Y54: 17429143
A55: Russell | B55: Estes | C55: Creative Director | D55: Square Lightning Communications & Design | E55: 1-10 employees | F55: Design Services | G55: Los Angeles, California, United States | I55: https://www.linkedin.com/in/russellestes | J55: https://www.linkedin.com/company/square-lightning-communications-design | K55: Creative Director at Square Lightning Communications & Design | L55: July 2020 - Present | O55: RECENT_ACTIVITY | P55: Top 5% most active in your ICP (LinkedIn) | R55: 0.96 | S55: 1.2 | T55: 2 | U55: Role and location align with ICP; industry matches; company size is slightly smaller. | V55: No | W55: 2026-09-07 09:24 | X55: NEW - not yet exported | Y55: 17429138
A56: Bayless | B56: Thompson | C56: Co-Founder + Creative Director | D56: Kidsister | E56: 1-10 employees | F56: Marketing Services | G56: Springfield, Missouri, United States | H56: https://www.behance.net/bayless | I56: https://www.linkedin.com/in/bayless-thompson | J56: https://www.linkedin.com/company/kidsister | K56: Strategic Marketing Creative | Graphic Designer & Copywriter | L56: April 2024 - Present | O56: RECENT_ACTIVITY | P56: Top 5% most active in your ICP (LinkedIn) | R56: 0.9 | S56: 1.2 | T56: 1.9 | U56: Founding/creative leadership aligns; US location; matching industry; near ICP size. | V56: No | W56: 2026-09-07 09:24 | X56: NEW - not yet exported | Y56: 17429135
A57: Samantha | B57: Hickey | C57: Owner & Creative Director | D57: Blue Coral Creative | E57: 1-10 employees | F57: Design Services | G57: Dayton, Ohio, United States | I57: https://www.linkedin.com/in/samhickey | J57: https://www.linkedin.com/company/blue-coral-creative | K57: Creative Director at Blue Coral Creative | L57: January 2021 - Present | O57: RECENT_ACTIVITY | P57: Top 5% most active in your ICP (LinkedIn) | R57: 0.92 | S57: 1.2 | T57: 2 | U57: Role maps to Creative Director; industry matches Design Services in US; company size is close to ICP bands; location is within ICP region. | V57: No | W57: 2026-09-07 09:24 | X57: NEW - not yet exported | Y57: 17429128
A58: Ravi Kumar | B58: Sapata | C58: Founder/CEO | D58: PropTechBuzz | E58: 11-50 employees | F58: Marketing Services | G58: Dover, Delaware, United States | H58: https://proptechbuzz.com | I58: https://www.linkedin.com/in/yoursproductly | J58: https://www.linkedin.com/company/proptechbuzz/ | K58: Founder/CEO PropTechBuzz | L58: 6/6/2022 - now | O58: RECENT_ACTIVITY | P58: Top 5% most active in your ICP (LinkedIn) | R58: 1 | S58: 1.2 | T58: 2.1 | U58: Founder/CEO in Marketing Services with US location and 11-50 staff fit ICP. | V58: No | W58: 2026-09-07 09:24 | X58: NEW - not yet exported | Y58: 17429115
A59: Yagmur | B59: Altan | C59: Creative Director | D59: 100Percent | E59: 2 - 10 | F59: Advertising Services | G59: Los Angeles Metropolitan Area | H59: www.yagmuraltan.com | I59: https://www.linkedin.com/in/yagmur-altan | J59: https://www.linkedin.com/company/100percentagency | K59: Creative Director / Animation Director | L59: February 2026 - Present | O59: RECENT_ACTIVITY | P59: Top 5% most active in your ICP (LinkedIn) | R59: 1 | S59: 1.2 | T59: 2.1 | U59: Role, industry, location, and company size align with the ICP requirements. | V59: No | W59: 2026-09-07 09:24 | X59: NEW - not yet exported | Y59: 17429107
A60: Lashay B. | B60: J. | C60: Founder & Creative Director | D60: HAUS of SHAYB | E60: 1-10 employees | F60: Marketing Services | G60: Charlotte, North Carolina, United States | I60: https://www.linkedin.com/in/labjones | J60: https://www.linkedin.com/company/haus-of-shayb/ | K60: Brand Strategist | Merchandising Professional | AI Creative Director | Founder at Haus of Shay B | L60: 5/01/2026 - now | O60: RECENT_ACTIVITY | P60: Top 5% most active in your ICP (LinkedIn) | R60: 0.92 | S60: 1.2 | T60: 2 | U60: Role and industry align with ICP; location and company size are a close fit. | V60: No | W60: 2026-09-07 09:24 | X60: NEW - not yet exported | Y60: 17429090
A61: Jamison | B61: Taylor, MBA | C61: Founder & Creative Director | D61: Artisyn & Co. | E61: 1-10 employees | F61: Marketing Services | G61: Afton, Virginia, United States | H61: www.merakilifecoaching.com | I61: https://www.linkedin.com/in/jamisontaylor | J61: https://linkedin.com/company/116002108 | K61: Founder & Creative Director, Artisyn & Co. | Building brands with empathy, creativity, and business design | L61: 03/01/2026 - Present | O61: RECENT_ACTIVITY | P61: Top 5% most active in your ICP (LinkedIn) | R61: 0.89 | S61: 1.2 | T61: 1.9 | U61: Founder & Creative Director at a US marketing services firm aligns with the ICP; location and industry match; company size is one band smaller than the ICP. | V61: No | W61: 2026-09-07 09:23 | X61: NEW - not yet exported | Y61: 17429084
A62: Chris | B62: Oyegoke | C62: Founder & Creative Director | D62: Urban Events Media | E62: 1-10 employees | F62: Marketing Services | G62: Dallas-Fort Worth Metroplex | I62: https://www.linkedin.com/in/chris-oyegoke-504364135 | J62: https://www.linkedin.com/company/urban-events-media | K62: Helping construction, energy & data companies build authority through strategic content | L62: January 2025 - Present | O62: RECENT_ACTIVITY | P62: Top 5% most active in your ICP (LinkedIn) | R62: 0.86 | S62: 1.2 | T62: 1.9 | U62: Founder/Creative Director in Marketing Services US aligns with ICP. | V62: No | W62: 2026-09-07 09:23 | X62: NEW - not yet exported | Y62: 17429083
A63: Olisa | B63: Ogbolu | C63: Creative Director | D63: LSMK | E63: 1-10 employees | F63: Design Services | G63: United States | H63: http://be.net/lsmkstudios | I63: https://www.linkedin.com/in/olisaogbolu | J63: https://linkedin.com/company/117924226 | K63: Art Direction | Design | Photography | Music | L63: 02/01/2015 - Present | O63: RECENT_ACTIVITY | P63: Top 5% most active in your ICP (LinkedIn) | R63: 0.9 | S63: 1.2 | T63: 2 | U63: Role aligned to ICP and location/industry fit for US design services | V63: No | W63: 2026-09-07 09:23 | X63: NEW - not yet exported | Y63: 17429072
A64: Niall | B64: Booker | C64: President / Art Director / Creative Director | D64: MultiPersona | E64: 1-10 employees | F64: Design Services | G64: Los Angeles Metropolitan Area | H64: http://www.multipersona.com | I64: https://www.linkedin.com/in/niallbooker | J64: https://www.linkedin.com/company/multipersona | K64: Art Director and Senior CG Environment and DMP TD and Artist | L64: May 2008 - Present | O64: RECENT_ACTIVITY | P64: Top 5% most active in your ICP (LinkedIn) | R64: 0.88 | S64: 1.2 | T64: 1.9 | U64: Role aligns with ICP titles; industry and location match US design services; company size is close to ICP range. | V64: No | W64: 2026-09-07 09:23 | X64: NEW - not yet exported | Y64: 17429069
A65: Annie | B65: Bradford | C65: Founder/Creative Director | D65: Bonfire Creative | E65: 1-10 employees | F65: Marketing Services | G65: Austin, Texas, United States | I65: https://www.linkedin.com/in/annie-bradford-395b8751 | J65: https://www.linkedin.com/company/bonfire-creative | K65: Photographer + Director at Bonfire Creative | L65: January 2024 - Present | O65: RECENT_ACTIVITY | P65: Top 5% most active in your ICP (LinkedIn) | R65: 0.81 | S65: 1.2 | T65: 1.8 | U65: Founder/Creative Director at a US-based marketing services agency aligns with ICP roles and location. | V65: No | W65: 2026-09-07 09:23 | X65: NEW - not yet exported | Y65: 17429062
A66: Christian | B66: Quinones | C66: Creative Director | D66: Made For Kings | E66: 1-10 employees | F66: Design Services | G66: Brooklyn, New York, United States | H66: http://www.madeforkings.com | I66: https://www.linkedin.com/in/christian-quinones-35219621 | J66: https://www.linkedin.com/company/made-for-kings | K66: Creative Director | L66: October 2009 - Present | O66: RECENT_ACTIVITY | P66: Top 5% most active in your ICP (LinkedIn) | R66: 0.98 | S66: 1.2 | T66: 2.1 | U66: Creative Director in Design Services, US, with a 2-10 employee company aligns with ICP role, industry, location, and near ICP size. | V66: No | W66: 2026-09-07 09:23 | X66: NEW - not yet exported | Y66: 17429045
A67: Sarah | B67: Rainwater | C67: Founder + Creative Director | D67: Studio Rainwater | E67: 1-10 employees | F67: Design Services | G67: Providence, Rhode Island, United States | H67: https://www.linkedin.com/redir/redirect?url=http://www.studiorainwater.com&urlhash=K762&trk=public_profile_topcard-website | I67: https://www.linkedin.com/in/sarahrainwater | J67: https://www.linkedin.com/company/studiorainwater | K67: Brand and Design Strategist, Creative Director at Studio Rainwater | L67: 2008 - Present | O67: RECENT_ACTIVITY | P67: Top 5% most active in your ICP (LinkedIn) | R67: 0.92 | S67: 1.2 | T67: 2 | U67: Strong fit: Founder/Creative Director in Design Services, US-based, with near-matching company size. | V67: No | W67: 2026-09-07 09:23 | X67: NEW - not yet exported | Y67: 17429036
A68: Borzou | B68: Azabdaftari | C68: Founder & Creative Director | D68: NickelBronx | E68: 11-50 employees | F68: Marketing Services | G68: McLean, Virginia, United States | H68: https://nickelbronx.com | I68: https://www.linkedin.com/in/borzou | J68: https://www.linkedin.com/company/nickelbronx/ | K68: Founder & Creative Director, @NickelBronx | Keynote Speaker | Fractional Creative Leadership | Most things could be better. I help founders and brands close the gap. | L68: 01/4/2021 - now | O68: RECENT_ACTIVITY | P68: Top 5% most active in your ICP (LinkedIn) | R68: 0.96 | S68: 1.2 | T68: 2 | U68: Strong fit: Founder/Creative Director in US marketing services with 11-50 staff. | V68: No | W68: 2026-09-07 09:23 | X68: NEW - not yet exported | Y68: 17429027
A69: Meg | B69: Goeman | C69: Creative Director | D69: Sol Design | E69: 1-10 employees | F69: Design Services | G69: Grand Rapids, Michigan, United States | H69: https://meggoeman.com/ | I69: https://www.linkedin.com/in/meahgangoeman | J69: https://www.linkedin.com/company/design-with-sol | K69: Creative Director | Graphic Designer | L69: June 2023 - Present | O69: RECENT_ACTIVITY | P69: Top 5% most active in your ICP (LinkedIn) | R69: 0.87 | S69: 1.2 | T69: 1.9 | U69: Role matches ICP and location/industry align well with the ICP. | V69: No | W69: 2026-09-07 09:23 | X69: NEW - not yet exported | Y69: 17429016
A70: Sara | B70: Malough | C70: Founder & CEO | D70: JANE Media Services | E70: 1-10 employees | F70: Marketing Services | G70: Riverbank, California, United States | I70: https://www.linkedin.com/in/sara-malough-53a4118a | J70: https://www.linkedin.com/company/jane-media-services | K70: Founder & CEO @ Jane Media Services | Digital Marketing, Content Creation, Brand Activations | L70: January 2018 - Present | O70: RECENT_ACTIVITY | P70: Top 5% most active in your ICP (LinkedIn) | R70: 0.89 | S70: 1.2 | T70: 1.9 | U70: Founder & CEO of a Marketing Services firm in the US aligns with ICP. | V70: No | W70: 2026-09-07 09:23 | X70: NEW - not yet exported | Y70: 17428994
A71: Adam | B71: Dell | C71: Creative Director | D71: Purple Frog | E71: 11-50 employees | F71: Marketing Services | G71: Irvington, New York, United States | H71: https://www.acdell.com/portfolio/ | I71: https://www.linkedin.com/in/acdell1 | J71: https://www.linkedin.com/company/purple-frog | K71: Multidisciplinary Creative Tech | L71: January 2026 - Present | O71: RECENT_ACTIVITY | P71: Top 5% most active in your ICP (LinkedIn) | R71: 0.9 | S71: 1.2 | T71: 2 | U71: Creative Director aligns with ICP role; location, industry, and company size match. | V71: No | W71: 2026-09-07 09:23 | X71: NEW - not yet exported | Y71: 17428982
A72: Jordan | B72: Frank | C72: Founder, CEO | D72: Courageous | E72: 2 - 10 | F72: Advertising Services | G72: Boulder, Colorado, United States | H72: https://courageoushq.com | I72: https://www.linkedin.com/in/jordan-frank-46085625 | J72: https://www.linkedin.com/company/courageous-growth-agency/ | K72: Founder, CEO | L72: 1/9/2023 - now | O72: RECENT_ACTIVITY | P72: Top 5% most active in your ICP (LinkedIn) | R72: 0.95 | S72: 1.2 | T72: 2 | U72: Founder/CEO aligns with ICP roles in advertising services in the US. | V72: No | W72: 2026-09-07 09:23 | X72: NEW - not yet exported | Y72: 17428976
A73: Sofia | B73: Mondelo | C73: Founder + Creative Director | D73: 28 Cylinders | E73: 1-10 employees | F73: Marketing Services | G73: Miami, Florida, United States | H73: scmondelo.com | I73: https://www.linkedin.com/in/sofia-mondelo-74b414173 | J73: https://www.linkedin.com/company/28-cylinders | K73: Creative Director + Founder at 28 Cylinders | Creative Operations + Project Manager | Story-Led Content + Systems Thinker | Bilingual | L73: 2023 - Present | O73: RECENT_ACTIVITY | P73: Top 5% most active in your ICP (LinkedIn) | R73: 0.88 | S73: 1.2 | T73: 1.9 | U73: Founder/Creative Director in Marketing Services US; close to ICP size band. | V73: No | W73: 2026-09-07 09:23 | X73: NEW - not yet exported | Y73: 17428945
A74: Belinda | B74: Chen | C74: Creative Director | D74: Superficial | E74: 1-10 employees | F74: Design Services | G74: New York, New York, United States | H74: http://www.superficial.studio | I74: https://www.linkedin.com/in/belinda-chen-ab305258 | J74: https://www.linkedin.com/company/superficial | K74: Creative Director at Superficial | L74: September 2016 - Present | O74: RECENT_ACTIVITY | P74: Top 5% most active in your ICP (LinkedIn) | R74: 0.9 | S74: 1.2 | T74: 2 | U74: Role aligns with ICP and industry matches; located in the US, with a near-ICP company size. | V74: No | W74: 2026-09-07 09:23 | X74: NEW - not yet exported | Y74: 17428939
A75: Alejandra | B75: Dunphy | C75: Creative Director | D75: A+D Interior Design Studio | E75: 1-10 employees | F75: Design Services | G75: Atlanta, Georgia, United States | H75: http://www.a-dstudio.com | I75: https://www.linkedin.com/in/alejandra-dunphy-078a598 | J75: https://www.linkedin.com/company/adstudioatlanta | K75: Creative Director at A+D Interior Design Studio. Adjunct Professor, Interior Design | L75: September 2008 - Present | O75: RECENT_ACTIVITY | P75: Top 5% most active in your ICP (LinkedIn) | R75: 0.88 | S75: 1.2 | T75: 1.9 | U75: Creative Director in Design Services, US location, company size near ICP band; role maps to ICP title. | V75: No | W75: 2026-09-07 09:23 | X75: NEW - not yet exported | Y75: 17428927
A76: Gabriel | B76: Lindman | C76: Founder & Creative Director | D76: Illume Design Co | E76: Myself Only | F76: Design Services | G76: Greater Indianapolis | I76: https://www.linkedin.com/in/gabriellindman | J76: https://www.linkedin.com/company/illumedesignco | K76: Founder & Creative Director @ Illume | Brand Strategy, Identity, & Design | L76: September 2024 - Present | O76: RECENT_ACTIVITY | P76: Top 5% most active in your ICP (LinkedIn) | R76: 0.9 | S76: 1.2 | T76: 2 | U76: Role maps to Founder/Creative Director and location/industry align with ICP. | V76: No | W76: 2026-09-07 09:23 | X76: NEW - not yet exported | Y76: 17428922
A77: Mason | B77: E | C77: CEO and Creative Director | D77: DigiMade Studios | E77: 1-10 employees | F77: Design Services | G77: Austin, Texas, United States | H77: https://www.digimadestudios.com/ | I77: https://www.linkedin.com/in/masonespedal | J77: https://www.linkedin.com/company/digimade-studios | K77: CEO & Creative Director at DigiMade Studios | Beverage Branding & Can Design Expert | L77: March 2026 - Present | O77: RECENT_ACTIVITY | P77: Top 5% most active in your ICP (LinkedIn) | R77: 0.88 | S77: 1.2 | T77: 1.9 | U77: Role aligns with ICP as CEO/Creative Director in a US Design Services firm. | V77: No | W77: 2026-09-07 09:23 | X77: NEW - not yet exported | Y77: 17428912
A78: Chris | B78: Eden | C78: CEO and Creative Director | D78: Fenwick | E78: 1-10 employees | F78: Marketing Services | G78: San Francisco, California, United States | H78: http://www.fenwick.media | I78: https://www.linkedin.com/in/chrismattheweden | J78: https://linkedin.com/company/7952651 | K78: B2B creative director. Edits Rewild Magazine | L78: 10/01/2022 - Present | O78: RECENT_ACTIVITY | P78: Top 5% most active in your ICP (LinkedIn) | R78: 0.96 | S78: 1.2 | T78: 2 | U78: Strong alignment across title, industry, size, and location per ICP. | V78: No | W78: 2026-09-07 09:23 | X78: NEW - not yet exported | Y78: 17428905
A79: Tina | B79: Fascetti | C79: Founder/Partner Global Creative Director | D79: The Jump | E79: 1-10 employees | F79: Marketing Services | G79: Newtown, Pennsylvania, United States | H79: https://www.linkedin.com/redir/redirect?url=https://thejump.info/&urlhash=2uBb&trk=public_profile_topcard-website | I79: https://www.linkedin.com/in/tinafascetti | J79: https://www.linkedin.com/company/the-jump-brand-consultants | K79: Founder/Partner Global Creative Director, The Jump | L79: February 2026 - Present | O79: RECENT_ACTIVITY | P79: Top 5% most active in your ICP (LinkedIn) | R79: 0.94 | S79: 1.2 | T79: 2 | U79: Founder/Creative leadership aligns with ICP; industry and US location match; company size is within one band off of ICP. | V79: No | W79: 2026-09-07 09:23 | X79: NEW - not yet exported | Y79: 17428882
A80: Zippy | B80: Burman | C80: Founder and Creative Director | D80: Greetings From Studio | E80: 1-10 employees | F80: Design Services | G80: Los Angeles, California, United States | H80: https://greetingsfrom.studio/ | I80: https://www.linkedin.com/in/zippy-burman | J80: https://www.linkedin.com/company/greetings-from-studio | K80: Founder and Creative Director at Greetings From | L80: March 2018 - Present | O80: RECENT_ACTIVITY | P80: Top 5% most active in your ICP (LinkedIn) | R80: 0.96 | S80: 1.2 | T80: 2 | U80: Strong fit: Founder/Creative Director in Design Services, US location, and company size close to ICP. | V80: No | W80: 2026-09-07 09:23 | X80: NEW - not yet exported | Y80: 17428871
A81: Emilie | B81: Hunter | C81: Client Success Manager | D81: Drum Creative | E81: 11-50 employees | F81: Marketing Services | G81: Greenville, South Carolina, United States | I81: https://www.linkedin.com/in/emiliehunter | J81: https://www.linkedin.com/company/drum-creative | K81: Client Strategy, Growth, & Success at Drum Creative | L81: April 2026 - Present | O81: RECENT_ACTIVITY | P81: Top 5% most active in your ICP (LinkedIn) | R81: 0.96 | S81: 1.2 | T81: 2 | U81: Role aligns with ICP; industry, location, and company size match the ICP. | V81: No | W81: 2026-09-07 09:23 | X81: NEW - not yet exported | Y81: 17428868
A82: Seonhye | B82: Oh | C82: Creative Director | D82: EPIC CONTENT | E82: 11-50 employees | F82: Marketing Services | G82: Williamsburg, Virginia, United States | I82: https://www.linkedin.com/in/sgraceoh | J82: https://www.linkedin.com/company/epiccontentagency | K82: Creative Director, Designer & Educator | L82: 2018 - Present | O82: RECENT_ACTIVITY | P82: Top 5% most active in your ICP (LinkedIn) | R82: 0.96 | S82: 1.2 | T82: 2 | U82: Role aligns with ICP (Creative Director); industry, location, and company size match. | V82: No | W82: 2026-09-07 09:23 | X82: NEW - not yet exported | Y82: 17428855
A83: Rebecca | B83: Bartlett | C83: Founder & Creative Director | D83: Bartlett Brands | E83: 1-10 employees | F83: Marketing Services | G83: San Francisco, California, United States | H83: http://bartlettbrands.com | I83: https://www.linkedin.com/in/rebecca-bartlett-2226614 | J83: https://www.linkedin.com/company/bartlett-brands | K83: Principal & Executive Creative Director @ Bartlett Brands | Brand Builder | Advisor | Investor | L83: October 2011 - Present | O83: RECENT_ACTIVITY | P83: Top 5% most active in your ICP (LinkedIn) | R83: 0.97 | S83: 1.2 | T83: 2.1 | U83: Founding leadership role in US marketing services aligns with ICP requirements. | V83: No | W83: 2026-09-07 09:23 | X83: NEW - not yet exported | Y83: 17428823
A84: Satyen | B84: Rao | C84: Founder & Creative Director | D84: Satyate | E84: 2 - 10 | F84: Advertising Services | G84: New York City Metropolitan Area, United States | H84: https://satyate.com | I84: https://www.linkedin.com/in/satyenr | J84: https://www.linkedin.com/company/satyate/ | K84: Creative Director. Founder. 13 years across news, social & brand. Built award-winning content studios at Ogilvy NY & Singapore. Coca-Cola · Merck · American Express. Now building Satyate. | L84: 2/01/2024 - now | O84: RECENT_ACTIVITY | P84: Top 5% most active in your ICP (LinkedIn) | R84: 0.93 | S84: 1.2 | T84: 2 | U84: Role aligns with ICP; industry matches Advertising Services; location and size align; strong overall fit. | V84: No | W84: 2026-09-07 09:23 | X84: NEW - not yet exported | Y84: 17428816
A85: Fletcher | B85: Martin | C85: Creative Director / Co-Founder | D85: a5 Branding & Digital | E85: 11-50 | F85: Design Services | G85: Greater Chicago Area | H85: http://www.a5inc.com | I85: https://www.linkedin.com/in/fletchmartin | J85: https://www.linkedin.com/company/a5-branding-and-digital | K85: Creative Director at a5 | L85: June 2000 - Present | O85: RECENT_ACTIVITY | P85: Top 5% most active in your ICP (LinkedIn) | R85: 1 | S85: 1.2 | T85: 2.1 | U85: Title, industry, company size, and US location closely match the ICP criteria. | V85: No | W85: 2026-09-07 09:23 | X85: NEW - not yet exported | Y85: 17428805
A86: Laura | B86: Grieve | C86: Creative Director | D86: Score Atlanta | E86: 51 - 200 | F86: Advertising Services | G86: Atlanta Metropolitan Area, United States | H86: https://scoreatl.com | I86: https://www.linkedin.com/in/lauragrieve | J86: https://www.linkedin.com/company/score-atlanta/ | K86: Creative Director @ Score Atlanta | Graphic Design, Event Production | L86: 4/5/2022 - now | O86: RECENT_ACTIVITY | P86: Top 5% most active in your ICP (LinkedIn) | R86: 0.96 | S86: 1.2 | T86: 2 | U86: Role matches ICP (Creative Director) with location/industry alignment; company size is one band off from ICP. | V86: No | W86: 2026-09-07 09:23 | X86: NEW - not yet exported | Y86: 17428777
A87: Maggie | B87: Dougherty | C87: Co-founder & Creative Director | D87: emcee content & design | E87: 1-10 employees | F87: Design Services | G87: West Chester, Pennsylvania, United States | H87: https://theemceestudio.com/ | I87: https://www.linkedin.com/in/maggie-dougherty | J87: https://www.linkedin.com/company/emcee-studio | K87: Co-founder + Creative Director | L87: April 2021 - Present | O87: RECENT_ACTIVITY | P87: Top 5% most active in your ICP (LinkedIn) | R87: 0.88 | S87: 1.2 | T87: 1.9 | U87: Founder/Creative Director in Design Services based in the US; strong ICP fit. | V87: No | W87: 2026-09-07 09:23 | X87: NEW - not yet exported | Y87: 17428765
A88: Diana | B88: García | C88: Founder & Creative Director | D88: Veintidós Studio | E88: Myself Only | F88: Design Services | G88: Denver, Colorado, United States | H88: https://www.dianagrc.com/ | I88: https://www.linkedin.com/in/dianagrc | J88: https://www.linkedin.com/company/veintidós-studio | K88: Bilingual Graphic Designer | Creative Director & Branding Strategist | L88: July 2021 - Present | O88: RECENT_ACTIVITY | P88: Top 5% most active in your ICP (LinkedIn) | R88: 0.8 | S88: 1.2 | T88: 1.8 | U88: Founder/Creative Director aligns with ICP roles; location matches US; industry matches; company size diverges from ICP. | V88: No | W88: 2026-09-07 09:23 | X88: NEW - not yet exported | Y88: 17428752
A89: Meredith | B89: Mele | C89: Creative Director + Co-Founder | D89: Spruce + Furn | E89: 1-10 employees | F89: Design Services | G89: New York, New York, United States | H89: http://www.krop.com/mjmele | I89: https://www.linkedin.com/in/mjmele | J89: https://www.linkedin.com/company/spruce-and-furn | K89: Creative Director + Co-Founder at Spruce + Furn | L89: July 2014 - Present | O89: RECENT_ACTIVITY | P89: Top 5% most active in your ICP (LinkedIn) | R89: 0.93 | S89: 1.2 | T89: 2 | U89: Creative Director/Co-Founder in Design Services within US; strong fit. | V89: No | W89: 2026-09-07 09:23 | X89: NEW - not yet exported | Y89: 17428706
A90: Will | B90: P. | C90: Creative Director | D90: Saam3 Creative | E90: 2 - 10 | F90: Advertising Services | G90: Wanaque, New Jersey, United States | I90: https://www.linkedin.com/in/will-p-318a312 | J90: https://www.linkedin.com/company/saam3-creative | K90: Founder of Saam3 Creative | L90: January 2025 - Present | O90: RECENT_ACTIVITY | P90: Top 5% most active in your ICP (LinkedIn) | R90: 1 | S90: 1.2 | T90: 2.1 | U90: Role, industry, company size, and location align with the ICP. | V90: No | W90: 2026-09-07 09:23 | X90: NEW - not yet exported | Y90: 17428688
A91: Shaik | B91: Ridzwan | C91: Founder | Creative Director | D91: The Mighty Motor | E91: 1-10 employees | F91: Design Services | G91: Los Angeles, California, United States | H91: http://Themightymotor.com | I91: https://www.linkedin.com/in/shaikridzwan | J91: https://www.linkedin.com/company/mimocreate | K91: Creative Director | Founder at The Mighty Motor | Principal at MIMO.LA | L91: October 2009 - Present | O91: RECENT_ACTIVITY | P91: Top 5% most active in your ICP (LinkedIn) | R91: 0.9 | S91: 1.2 | T91: 2 | U91: Role matches ICP founder/creative director in US design services; industry aligns; company size slightly smaller but close; location matches US | V91: No | W91: 2026-09-07 09:23 | X91: NEW - not yet exported | Y91: 17428667
A92: Alexander | B92: Acker | C92: President, Creative Director | D92: Adventure House | E92: 1-10 employees | F92: Marketing Services | G92: New York, New York, United States | H92: https://adventurehousenyc.com | I92: https://www.linkedin.com/in/alexanderacker | J92: https://www.linkedin.com/company/adventure-house/ | K92: President | Founder | Digital Agency Leader | L92: 5/9/1998 - now | O92: RECENT_ACTIVITY | P92: Top 5% most active in your ICP (LinkedIn) | R92: 0.89 | S92: 1.2 | T92: 1.9 | U92: Role aligns with ICP; industry matches; location US; company size slightly small. | V92: No | W92: 2026-09-07 09:23 | X92: NEW - not yet exported | Y92: 17428655
A93: Kelsey | B93: Glassman | C93: Co-Founder & Creative Director | D93: Bread & Butter Designs | E93: 1-10 employees | F93: Design Services | G93: Denver, Colorado, United States | H93: http://www.kelseydenison.com | I93: https://www.linkedin.com/in/kelsey-glassman-aa362087 | J93: https://www.linkedin.com/company/bread-butter-designs | K93: Co-Founder & Creative Director @ Bread & Butter Designs | Branding, Product Design Leader | L93: January 2024 - Present | O93: RECENT_ACTIVITY | P93: Top 5% most active in your ICP (LinkedIn) | R93: 0.91 | S93: 1.2 | T93: 2 | U93: Role and company fit the ICP criteria with strong alignment in title, industry, location, and near-match company size. | V93: No | W93: 2026-09-07 09:23 | X93: NEW - not yet exported | Y93: 17428652
A94: Manuelita | B94: Rangel Sosa | C94: Founder / Creative Director | D94: We are SuperWorks | E94: 1-10 employees | F94: Design Services | G94: San Francisco, California, United States | H94: https://www.wearesuperworks.com/ | I94: https://www.linkedin.com/in/manuelita-antonio-rangel-sosa-50613331 | J94: https://www.linkedin.com/company/we-are-superworks | K94: Founder / Creative Director @ SuperWorks || Design Thinking, Brand Strategy, Product Design | L94: November 2015 - Present | O94: RECENT_ACTIVITY | P94: Top 5% most active in your ICP (LinkedIn) | R94: 0.96 | S94: 1.2 | T94: 2 | U94: Founder/Creative Director fits ICP role; industry and location are exact; company size is one band smaller than ICP, lowering but not disqualifying. | V94: No | W94: 2026-09-07 09:23 | X94: NEW - not yet exported | Y94: 17428649
A95: Hazel | B95: Imogen | C95: Founder & Creative Director | D95: Series Brand Studio | E95: 1-10 employees | F95: Marketing Services | G95: Los Angeles, California, United States | H95: http://www.twoparts.studio | I95: https://www.linkedin.com/in/hazelimogen | J95: https://www.linkedin.com/company/seriesbrandstudio | K95: Founder | Creative Director | Big-time-thinker | L95: October 2024 - Present | O95: RECENT_ACTIVITY | P95: Top 5% most active in your ICP (LinkedIn) | R95: 0.87 | S95: 1.2 | T95: 1.9 | U95: Founder & Creative Director at a Marketing Services agency in the US aligns with the ICP. | V95: No | W95: 2026-09-07 09:23 | X95: NEW - not yet exported | Y95: 17428636
A96: Daniel | B96: Souza | C96: Founder & Creative Director | D96: Element5 Creative | E96: 1-10 employees | F96: Marketing Services | G96: Salt Lake City Metropolitan Area | I96: https://www.linkedin.com/in/1danielsouza | J96: https://linkedin.com/company/116794216 | K96: Founder & Creative Director at Element5 Creative | I help small businesses get more customers with smart websites, AI tools, and marketing that actually works. Plain English. Real results. | L96: 05/01/2026 - Present | O96: RECENT_ACTIVITY | P96: Top 5% most active in your ICP (LinkedIn) | R96: 0.96 | S96: 1.2 | T96: 2 | U96: Role matches ICP; industry and location align; company size near ICP; strong fit. | V96: No | W96: 2026-09-07 09:23 | X96: NEW - not yet exported | Y96: 17428620
A97: Imani | B97: Lee | C97: Founder & Creative Director | D97: Live Stay Creative | E97: 1-10 employees | F97: Marketing Services | G97: Tampa, Florida, United States | H97: https://www.imanilenz.com/ | I97: https://www.linkedin.com/in/imanilenz | J97: https://www.linkedin.com/company/livestaycreative | K97: Creative Artist & Founder (Video. Photo. Music) | L97: April 2021 - Present | O97: RECENT_ACTIVITY | P97: Top 5% most active in your ICP (LinkedIn) | R97: 0.9 | S97: 1.2 | T97: 2 | U97: Founder & Creative Director aligns with ICP titles; industry and location match; company size is one band below ICP. | V97: No | W97: 2026-09-07 09:23 | X97: NEW - not yet exported | Y97: 17428573
A98: Rachel | B98: Holtin | C98: Founder, Creative Director | D98: Austin Foodstagram | E98: 1-10 employees | F98: Marketing Services | G98: Austin, Texas, United States | I98: https://www.linkedin.com/in/rachel-holtin-95b0004a | J98: https://www.linkedin.com/company/austin-foodstagram | K98: Founder, Creative Director at Austin Foodstagram | L98: May 2014 - Present | O98: RECENT_ACTIVITY | P98: Top 5% most active in your ICP (LinkedIn) | R98: 0.85 | S98: 1.2 | T98: 1.9 | U98: Role matches ICP and location aligns; company size is slightly off but acceptable. | V98: No | W98: 2026-09-07 09:23 | X98: NEW - not yet exported | Y98: 17428570
A99: John | B99: Oberbeck | C99: Founder & Creative Director | D99: JEO Creative | E99: 1-10 employees | F99: Design Services | G99: New York, New York, United States | I99: https://www.linkedin.com/in/john-eric-oberbeck-68475b2a | J99: https://www.linkedin.com/company/jeo-creative | K99: Founder & Creative Director, JEO Creative | L99: April 2023 - Present | O99: RECENT_ACTIVITY | P99: Top 5% most active in your ICP (LinkedIn) | R99: 1 | S99: 1.2 | T99: 2.1 | U99: Role, industry, company size, and location align with ICP requirements. | V99: No | W99: 2026-09-07 09:23 | X99: NEW - not yet exported | Y99: 17428553
A100: Jen | B100: Houser | C100: Founder + President | D100: Creative Springs | E100: 11-50 | F100: Marketing Services | G100: St Augustine, Florida, United States | H100: https://creativesprings.com | I100: https://www.linkedin.com/in/jen-h-houser | J100: https://www.linkedin.com/company/creativesprings | K100: Founder & President of Creative Springs | L100: September 2020 - Present | O100: RECENT_ACTIVITY | P100: Top 5% most active in your ICP (LinkedIn) | R100: 1 | S100: 1.2 | T100: 2.1 | U100: Role aligns with ICP Founder/President in a US Marketing Services firm. | V100: No | W100: 2026-09-07 09:23 | X100: NEW - not yet exported | Y100: 17428522
...

Sheet Summary
A1: Agency - Eikko leads — Gojiberry list 45132 (agent 'Agency - Eikko', id 29267)
A2: Source: Gojiberry API via Penji Gojiberry connector, pulled 2026-09-07 ~12:45 UTC (20:45 PHT). 'Previously exported' = LinkedIn URL matches one of the 2026-09-02 Dripify import files (Amanda Scott / Whitney Cole).
A4: Export status | B4: Leads
A5: NEW - not yet exported | B5: =COUNTIF(Leads!$X$2:$X$500,"NEW*") -> 238
A6: Previously exported (Amanda Scott, 2026-09-02) | B6: =COUNTIF(Leads!$X$2:$X$500,"Previously exported (Amanda Scott*") -> 131
A7: Previously exported (Whitney Cole, 2026-09-02) | B7: =COUNTIF(Leads!$X$2:$X$500,"Previously exported (Whitney Cole*") -> 130
A8: Total in list | B8: =SUM(B5:B7) -> 499
A10: Intent type (how Gojiberry found them) | B10: Leads | C10: Share
A11: RECENT_ACTIVITY | B11: =COUNTIF(Leads!$O$2:$O$500,A11) -> 192 | C11: =IF($B$8=0,0,B11/$B$8) -> 0.38476954
A12: LOOKALIKE | B12: =COUNTIF(Leads!$O$2:$O$500,A12) -> 163 | C12: =IF($B$8=0,0,B12/$B$8) -> 0.32665331
A13: RECENTLY_CHANGED_JOB | B13: =COUNTIF(Leads!$O$2:$O$500,A13) -> 53 | C13: =IF($B$8=0,0,B13/$B$8) -> 0.10621242
A14: SEARCH_KEYWORD | B14: =COUNTIF(Leads!$O$2:$O$500,A14) -> 48 | C14: =IF($B$8=0,0,B14/$B$8) -> 0.096192385
A15: INFLUENCER_PAGE_URL | B15: =COUNTIF(Leads!$O$2:$O$500,A15) -> 29 | C15: =IF($B$8=0,0,B15/$B$8) -> 0.058116232
A16: YOUR_PROFILE | B16: =COUNTIF(Leads!$O$2:$O$500,A16) -> 8 | C16: =IF($B$8=0,0,B16/$B$8) -> 0.016032064
A17: COMPETITOR_PAGE_URL | B17: =COUNTIF(Leads!$O$2:$O$500,A17) -> 6 | C17: =IF($B$8=0,0,B17/$B$8) -> 0.012024048
A18: Check: sum of intent types | B18: =SUM(B11:B17) -> 499
A20: Data quality | B20: Leads
A21: With email | B21: =COUNTIF(Leads!$M$2:$M$500,"?*") -> 0
A22: With phone | B22: =COUNTIF(Leads!$N$2:$N$500,"?*") -> 0
A23: Open to work | B23: =COUNTIF(Leads!$V$2:$V$500,"Yes") -> 0
A24: Total score ≥ 2.0 | B24: =COUNTIF(Leads!$T$2:$T$500,">=2") -> 261
A25: Average ICP fit score | B25: =IFERROR(AVERAGE(Leads!$R$2:$R$500),0) -> 0.90769539
A26: Added on 2026-09-07 (PHT) | B26: =COUNTIF(Leads!$W$2:$W$500,"2026-09-07*") -> 149
A27: Note: Gojiberry has enriched no emails or phones on this list (enrichment costs credits and was not run). Company-size labels vary because Gojiberry stores the raw LinkedIn value.
